Workbook

Sheet Assumptions
A1: Exhibit 5 | C1: Treasury Yields
A3: Maturity | B3: 44196 | C3: Average Month End from 2016 - 2020
A4: 3 Months | B4: 0.001 | C4: 0.011
A5: 1 Year | B5: 0.001 | C5: 0.013
A6: 5 Years | B6: 0.004 | C6: 0.017
A7: 10 Years | B7: 0.009 | C7: 0.02
A8: 20 Years | B8: 0.015 | C8: 0.023
A9: 30 Years | B9: 0.017 | C9: 0.025
A11: Exhibit 10 | C11: Debt Betas by Credit Rating Index, 2016-2020
A13: Rating | B13: Beta [1]
A14: AAA | B14: 0.04
A15: AA | B15: 0.08
A16: A | B16: 0.13
A17: BBB | B17: 0.27
A18: BB | B18: 0.35
A19: B | B19: 0.41
A20: CCC | B20: 0.62
A22: Table 1 | B22: Market Risk Premium (according to case study page 4)
A24: Source/Methodology | C24: MRP(%)
A25: 2021 CFO Survey | C25: 0.046
A26: 2021 Surveys | C26: 0.05
A27: 2021 Investor-Professional surveys | C27: 0.055
A28: Historical Data (1872-2021) | C28: 0.064

Sheet Returns
A1: Exhibit 9 | C1: Comparable Firms and the S&P 500, Stock Return Data, 2016-2020
A3: Month | B3: S&P 500 | C3: Las Vegas Sands | D3: MGM Resorts | E3: Caesars | F3: Penn Entertainment | G3: Wynn Resorts | H3: Churchill Downs | I3: Boyd Gaming | J3: Monarch | K3: Disney | L3: Netflix | M3: Live Nation | N3: Warner Brothers | O3: Madison Square Garden | P3: World Wrestling | Q3: Activision Blizzard | R3: Electronic Arts | S3: Take-Two Interactive | T3: Meta Platforms | U3: Twitter | V3: Match Group
A4: 42398 | B4: -0.05073534 | C4: 0.028740838 | D4: -0.11619716 | E4: -0.061818209 | F4: -0.11797754 | G4: -0.026738055 | H4: -0.023676626 | I4: -0.10367394 | J4: -0.088908389 | K4: -0.088123351 | L4: -0.19706243 | M4: -0.076109037 | N4: 0.034107938 | O4: -0.047713231 | P4: 0.0033631988 | Q4: -0.10049082 | R4: -0.060753826 | S4: -0.0040183524 | T4: 0.072138309 | U4: -0.27398446 | V4: -0.073800735
A5: 42429 | B5: -0.004128355 | C5: 0.070509985 | D5: -0.057270899 | E5: -0.030038709 | F5: -0.020523706 | G5: 0.23225436 | H5: -0.018242395 | I5: -0.027512621 | J5: -0.028019318 | K5: -0.0031309023 | L5: 0.017095027 | M5: -0.031277575 | N5: -0.093874596 | O5: 0.0059709121 | P5: -0.065921806 | Q5: -0.09046524 | R5: -0.0047253901 | S5: 0.037175819 | T5: -0.047143757 | U5: 0.078571528 | V5: -0.1322709
A6: 42460 | B6: 0.06599111 | C6: 0.085335575 | D6: 0.13259378 | E6: 0.14285707 | F6: 0.20592488 | G6: 0.13275941 | H6: 0.09039972 | I6: 0.19284067 | J6: -0.032803267 | K6: 0.039677564 | L6: 0.09442243 | M6: 0.014552056 | N6: 0.14519997 | O6: 0.073290326 | P6: 0.063397162 | Q6: 0.076728769 | R6: 0.029109633 | S6: 0.046679534 | T6: 0.067153014 | U6: -0.086644679 | V6: 0.015610659
A7: 42489 | B7: 0.00269937 | C7: -0.12635447 | D7: -0.006529911 | E7: 0.14597903 | F7: -0.033553109 | G7: -0.054907389 | H7: -0.092642762 | I7: -0.0977735 | J7: -0.023638187 | K7: 0.039774492 | L7: -0.11933879 | M7: -0.037203044 | N7: -0.046105474 | O7: -0.056383774 | P7: -0.057757672 | Q7: 0.018617053 | R7: -0.06443809 | S7: -0.092646614 | T7: 0.030499592 | U7: -0.11661628 | V7: 0.030741338
A8: 42521 | B8: 0.01532949 | C8: 0.024141753 | D8: 0.072770007 | E8: 0.136537 | F8: -0.028518233 | G8: 0.0949037 | H8: -0.064614631 | I8: 0.014485003 | J8: 0.11157899 | K8: -0.039124548 | L8: 0.13928692 | M8: 0.12430168 | N8: 0.01977301 | O8: 0.067206033 | P8: 0.055889443 | Q8: 0.13896133 | R8: 0.24090545 | S8: 0.13838501 | T8: 0.010460926 | U8: 0.041039698 | V8: 0.22807021
A9: 42551 | B9: 0.0009060735 | C9: -0.04390138 | D9: -0.0096280621 | E9: 0.019798663 | F9: -0.1097639 | G9: -0.057600342 | H9: 0.0067723566 | I9: -0.026969869 | J9: 0.040246136 | K9: -0.014110073 | L9: -0.10812125 | M9: -0.026915098 | N9: -0.094075434 | O9: 0.029725993 | P9: 0.054638598 | Q9: 0.009424421 | R9: -0.012898995 | S9: -0.025443373 | T9: -0.038128093 | U9: 0.11103808 | V9: 0.076785699
A10: 42580 | B10: 0.03560981 | C10: 0.16463554 | D10: 0.059655342 | E10: -0.04902928 | F10: 0.076702558 | G10: 0.08064869 | H10: 0.03774932 | I10: 0.065760925 | J10: 0.061902624 | K10: -0.011858544 | L10: -0.0025142473 | M10: 0.16680852 | N10: -0.0055489256 | O10: 0.059590742 | P10: 0.07278654 | Q10: 0.013373676 | R10: 0.0073917313 | S10: 0.059599217 | T10: 0.084529258 | U10: -0.015966911 | V10: 0.044776134
A11: 42613 | B11: -0.001219176 | C11: -0.0086871162 | D11: -0.003753134 | E11: -0.033910017 | F11: -0.05592544 | G11: -0.083001509 | H11: 0.13917486 | I11: -0.0056094141 | J11: 0.019717146 | K11: -0.0155289 | L11: 0.067945175 | M11: -0.025528839 | N11: 0.016739739 | O11: -0.01170742 | P11: 0.051645592 | Q11: 0.030129459 | R11: 0.06433443 | S11: 0.081881553 | T11: 0.017589157 | U11: 0.15444711 | V11: 0.027936542
A12: 42643 | B12: -0.001234483 | C12: 0.16032667 | D12: 0.089577287 | E12: 0.0071633509 | F12: -0.043018378 | G12: 0.090685159 | H12: -0.020283831 | I12: 0.014359009 | J12: 0.058007527 | K12: -0.01693837 | L12: 0.011287902 | M12: 0.028443122 | N12: 0.055272434 | O12: -0.062219709 | P12: 0.031295076 | Q12: 0.07082428 | R12: 0.051335689 | S12: 0.037037048 | T12: 0.017047267 | U12: 0.1998959 | V12: 0.098826453
A13: 42674 | B13: -0.01942562 | C13: 0.0059089353 | D13: 0.005378386 | E13: -0.13940255 | F13: -0.047162816 | G13: -0.02946002 | H13: -0.070720911 | I13: -0.097067744 | J13: -0.06038937 | K13: -0.0018306932 | L13: 0.26707253 | M13: 0.0069141388 | N13: -0.030089132 | O13: -0.023139119 | P13: -0.169953 | Q13: -0.025507925 | R13: -0.080562115 | S13: -0.015306176 | T13: 0.021205278 | U13: -0.22125807 | V13: 0.015176984
A14: 42704 | B14: 0.03417445 | C14: 0.082757376 | D14: 0.097057663 | E14: 0.1363636 | F14: 0.027068788 | G14: 0.083976671 | H14: 0.13544123 | I14: 0.054871194 | J14: 0.052008439 | K14: 0.069371022 | L14: -0.063025564 | M14: 0.00036141052 | N14: 0.037533492 | O14: 0.049247649 | P14: 0.062217213 | Q14: -0.15195733 | R14: 0.009169654 | S14: 0.10903357 | T14: -0.095961578 | U14: 0.030083509 | V14: -0.0044296747
A15: 42734 | B15: 0.01820075 | C15: -0.13626933 | D15: 0.0041797576 | E15: 0.23272733 | F15: 0.038403634 | G15: -0.15177955 | H15: -0.017309008 | I15: 0.070594475 | J15: 0.036173698 | K15: 0.059322018 | L15: 0.058119684 | M15: -0.039017338 | N15: 0.011812465 | O15: -0.012266787 | P15: -0.013844572 | Q15: -0.01365747 | R15: -0.0060574929 | S15: 0.0012187969 | T15: -0.02845799 | U15: -0.11844243 | V15: -0.048943225
... A63: 44196 | B63: 0.03712141 | C63: 0.069825873 | D63: 0.11548673 | E63: 0.090281762 | F63: 0.23385718 | G63: 0.12268659 | H63: 0.086104907 | I63: 0.11509474 | J63: 0.10865628 | K63: 0.22410648 | L63: 0.10195632 | M63: 0.11926887 | N63: 0.11817169 | O63: 0.086776935 | P63: 0.11919141 | Q63: 0.16821834 | R63: 0.12540123 | S63: 0.15112735 | T63: -0.013755994 | U63: 0.16426583 | V63: 0.086057

Sheet Equity_Betas
A1: Table 2 | B1: Equity Betas: five years regression vs S&P 500 (from Returns)
A2: Method: βe = SLOPE(firm returns, S&P 500 returns) over Jan 2016 – Dec 2020
A4: Firm | B4: Equity Beta (βe) | C4: R² | D4: StDev of returns | E4: Intercept (α) | F4: GICS Group
A5: Penn Entertainment | B5: =SLOPE(Returns!$F$4:$F$63,Returns!$B$4:$B$63) -> 2.7915455 | C5: =RSQ(Returns!$F$4:$F$63,Returns!$B$4:$B$63) -> 0.37958265 | D5: =_xlfn.STDEV.S(Returns!$F$4:$F$63) -> 0.19937676 | E5: =INTERCEPT(Returns!$F$4:$F$63,Returns!$B$4:$B$63) -> 0.016136255 | F5: Casinos & Gaming
A6: Caesars | B6: =SLOPE(Returns!$E$4:$E$63,Returns!$B$4:$B$63) -> 3.143658 | C6: =RSQ(Returns!$E$4:$E$63,Returns!$B$4:$B$63) -> 0.47315718 | D6: =_xlfn.STDEV.S(Returns!$E$4:$E$63) -> 0.20110162 | E6: =INTERCEPT(Returns!$E$4:$E$63,Returns!$B$4:$B$63) -> 0.020141742 | F6: Casinos & Gaming
A7: Churchill Downs | B7: =SLOPE(Returns!$H$4:$H$63,Returns!$B$4:$B$63) -> 1.3628826 | C7: =RSQ(Returns!$H$4:$H$63,Returns!$B$4:$B$63) -> 0.42534139 | D7: =_xlfn.STDEV.S(Returns!$H$4:$H$63) -> 0.091954423 | E7: =INTERCEPT(Returns!$H$4:$H$63,Returns!$B$4:$B$63) -> 0.013161868 | F7: Casinos & Gaming
A8: Boyd Gaming | B8: =SLOPE(Returns!$I$4:$I$63,Returns!$B$4:$B$63) -> 2.2385028 | C8: =RSQ(Returns!$I$4:$I$63,Returns!$B$4:$B$63) -> 0.62859062 | D8: =_xlfn.STDEV.S(Returns!$I$4:$I$63) -> 0.12423864 | E8: =INTERCEPT(Returns!$I$4:$I$63,Returns!$B$4:$B$63) -> -0.0033897717 | F8: Casinos & Gaming
A9: MGM Resorts | B9: =SLOPE(Returns!$D$4:$D$63,Returns!$B$4:$B$63) -> 2.4257071 | C9: =RSQ(Returns!$D$4:$D$63,Returns!$B$4:$B$63) -> 0.63483027 | D9: =_xlfn.STDEV.S(Returns!$D$4:$D$63) -> 0.13396537 | E9: =INTERCEPT(Returns!$D$4:$D$63,Returns!$B$4:$B$63) -> -0.011211747 | F9: Casinos & Gaming
A10: Wynn Resorts | B10: =SLOPE(Returns!$G$4:$G$63,Returns!$B$4:$B$63) -> 2.3769287 | C10: =RSQ(Returns!$G$4:$G$63,Returns!$B$4:$B$63) -> 0.51626541 | D10: =_xlfn.STDEV.S(Returns!$G$4:$G$63) -> 0.1455669 | E10: =INTERCEPT(Returns!$G$4:$G$63,Returns!$B$4:$B$63) -> -0.0059764895 | F10: Casinos & Gaming
A11: Las Vegas Sands | B11: =SLOPE(Returns!$C$4:$C$63,Returns!$B$4:$B$63) -> 1.3474389 | C11: =RSQ(Returns!$C$4:$C$63,Returns!$B$4:$B$63) -> 0.44415887 | D11: =_xlfn.STDEV.S(Returns!$C$4:$C$63) -> 0.088965762 | E11: =INTERCEPT(Returns!$C$4:$C$63,Returns!$B$4:$B$63) -> -0.0022482181 | F11: Casinos & Gaming
A12: Monarch | B12: =SLOPE(Returns!$J$4:$J$63,Returns!$B$4:$B$63) -> 1.6613447 | C12: =RSQ(Returns!$J$4:$J$63,Returns!$B$4:$B$63) -> 0.49586114 | D12: =_xlfn.STDEV.S(Returns!$J$4:$J$63) -> 0.10381562 | E12: =INTERCEPT(Returns!$J$4:$J$63,Returns!$B$4:$B$63) -> 0.0037961426 | F12: Casinos & Gaming

Sheet Leverage
A1: Exhibit 8 | B1: Comparable Firms, Leverage
B2: 2016-2020 Average Quarter-End | E2: Year-End 2020
A4: Firm | B4: Book Leverage (%) | C4: Market Leverage (%) | D4: Credit Rating | E4: Cash ($M) | F4: Debt ($M) | G4: Book Equity | H4: Market Equity
A5: Penn Entertainment | B5: 0.97 | C5: 0.71 | D5: B | E5: 1854 | F5: 10906 | G5: 2633 | H5: 13448
A6: Caesars | B6: 0.74 | C6: 0.53 | D6: B | E6: 1758 | F6: 26813 | G6: 5016 | H6: 15452
A7: Churchill Downs | B7: 0.66 | C7: 0.22 | D7: BB | E7: 67 | F7: 1643 | G7: 367 | H7: 7694
A8: Boyd Gaming | B8: 0.77 | C8: 0.55 | D8: B | E8: 519 | F8: 4716 | G8: 1124 | H8: 4800
A9: MGM Resorts | B9: 0.66 | C9: 0.47 | D9: BB | E9: 5102 | F9: 20901 | G9: 6505 | H9: 15576
A10: Wynn Resorts | B10: 0.91 | C10: 0.4 | D10: BB | E10: 3482 | F10: 12647 | G10: -352 | H10: 12173
A11: Las Vegas Sands | B11: 0.59 | C11: 0.16 | D11: BBB | E11: 2121 | F11: 14225 | G11: 2973 | H11: 45525
A12: Monarch | B12: 0.13 | C12: 0.07 | D12: A | E12: 28 | F12: 181 | G12: 368 | H12: 1128

Sheet Asset_Betas
A1: Table 3 | B1: Asset Betas: Unlevered by βa = (1 − Leverage)·βe + Leverage·βd
A3: Firm | B3: βe | C3: Market Leverage | D3: Rating | E3: βd | F3: βa | G3: Group
A4: Penn Entertainment | B4: =Equity_Betas!B5 -> 2.7915455 | C4: =Leverage!C5 -> 0.71 | D4: =Leverage!D5 -> B | E4: =VLOOKUP(D4, Assumptions!$A$14:$B$20, 2, FALSE()) -> 0.41 | F4: =(1-C4)*B4 + C4*E4 -> 1.1006482 | G4: Casinos & Gaming
A5: Caesars | B5: =Equity_Betas!B6 -> 3.143658 | C5: =Leverage!C6 -> 0.53 | D5: =Leverage!D6 -> B | E5: =VLOOKUP(D5, Assumptions!$A$14:$B$20, 2, FALSE()) -> 0.41 | F5: =(1-C5)*B5 + C5*E5 -> 1.6948193 | G5: Casinos & Gaming
A6: Churchill Downs | B6: =Equity_Betas!B7 -> 1.3628826 | C6: =Leverage!C7 -> 0.22 | D6: =Leverage!D7 -> BB | E6: =VLOOKUP(D6, Assumptions!$A$14:$B$20, 2, FALSE()) -> 0.35 | F6: =(1-C6)*B6 + C6*E6 -> 1.1400484 | G6: Casinos & Gaming
A7: Boyd Gaming | B7: =Equity_Betas!B8 -> 2.2385028 | C7: =Leverage!C8 -> 0.55 | D7: =Leverage!D8 -> B | E7: =VLOOKUP(D7, Assumptions!$A$14:$B$20, 2, FALSE()) -> 0.41 | F7: =(1-C7)*B7 + C7*E7 -> 1.2328262 | G7: Casinos & Gaming
A8: MGM Resorts | B8: =Equity_Betas!B9 -> 2.4257071 | C8: =Leverage!C9 -> 0.47 | D8: =Leverage!D9 -> BB | E8: =VLOOKUP(D8, Assumptions!$A$14:$B$20, 2, FALSE()) -> 0.35 | F8: =(1-C8)*B8 + C8*E8 -> 1.4501247 | G8: Casinos & Gaming
A9: Wynn Resorts | B9: =Equity_Betas!B10 -> 2.3769287 | C9: =Leverage!C10 -> 0.4 | D9: =Leverage!D10 -> BB | E9: =VLOOKUP(D9, Assumptions!$A$14:$B$20, 2, FALSE()) -> 0.35 | F9: =(1-C9)*B9 + C9*E9 -> 1.5661572 | G9: Casinos & Gaming
A10: Las Vegas Sands | B10: =Equity_Betas!B11 -> 1.3474389 | C10: =Leverage!C11 -> 0.16 | D10: =Leverage!D11 -> BBB | E10: =VLOOKUP(D10, Assumptions!$A$14:$B$20, 2, FALSE()) -> 0.27 | F10: =(1-C10)*B10 + C10*E10 -> 1.1750487 | G10: Casinos & Gaming
A11: Monarch | B11: =Equity_Betas!B12 -> 1.6613447 | C11: =Leverage!C12 -> 0.07 | D11: =Leverage!D12 -> A | E11: =VLOOKUP(D11, Assumptions!$A$14:$B$20, 2, FALSE()) -> 0.13 | F11: =(1-C11)*B11 + C11*E11 -> 1.5541506 | G11: Casinos & Gaming
A13: Table 4 | B13: Primary Peer Set (Top 6 US Casino Firms)
A14: Firms included: | B14: Penn Entertainment, Ceasars, Boyd Gaming, MGM Resorts, Wynn Resorts, Churchill Downs
A15: Average βa for the firms included | B15: =AVERAGE(F4:F9) -> 1.364104
A17: Table 5 | B17: Other Peer Sets
A18: Competition to DraftKings (Wynn Resorts, Ceasers, Penn Entertainment, MGM Resorts) | B18: =AVERAGE(F4,F5,F8,F9) -> 1.4529374
A19: Whole industry (all casinos) | B19: =AVERAGE(F4:F11) -> 1.3642279

Sheet WACC_Sensitivity
A1: Table 6 | B1: WACC Sensitivity: Peer Set × (rf, MRP)
A2: Method: WACC = rf + βa × MRP
A4: Peer Set | B4: Asset Beta (βa​) | C4: rf​=0.9%MRP=5.0% | D4: rf​=2.0%MRP=5.0% | E4: rf​=2.0%MRP=6.4% | F4: rf​=0.9%MRP=6.4%
A5: Primary: 6 US Casino Ops | B5: =Asset_Betas!B15 -> 1.364104 | C5: =Assumptions!$B$7 + WACC_Sensitivity!B5*Assumptions!$C$26 -> 0.077205201 | D5: =Assumptions!$C$7 + WACC_Sensitivity!B5*Assumptions!$C$26 -> 0.088205201 | E5: =Assumptions!$C$7 + WACC_Sensitivity!B5*Assumptions!$C$28 -> 0.10730266 | F5: =Assumptions!$B$7 + WACC_Sensitivity!B5*Assumptions!$C$28 -> 0.096302657
A6: 4 Direct OSB Competitors | B6: =Asset_Betas!B18 -> 1.4529374 | C6: =Assumptions!$B$7 + WACC_Sensitivity!B6*Assumptions!$C$26 -> 0.081646868 | D6: =Assumptions!$C$7 + WACC_Sensitivity!B6*Assumptions!$C$26 -> 0.092646868 | E6: =Assumptions!$C$7 + WACC_Sensitivity!B6*Assumptions!$C$28 -> 0.11298799 | F6: =Assumptions!$B$7 + WACC_Sensitivity!B6*Assumptions!$C$28 -> 0.10198799
A7: All 8 Casinos & Gaming | B7: =Asset_Betas!B19 -> 1.3642279 | C7: =Assumptions!$B$7 + WACC_Sensitivity!B7*Assumptions!$C$26 -> 0.077211396 | D7: =Assumptions!$C$7 + WACC_Sensitivity!B7*Assumptions!$C$26 -> 0.088211396 | E7: =Assumptions!$C$7 + WACC_Sensitivity!B7*Assumptions!$C$28 -> 0.10731059 | F7: =Assumptions!$B$7 + WACC_Sensitivity!B7*Assumptions!$C$28 -> 0.096310587
